[{"fullname":"tainara","html":"<p class=\"TweetTextSize TweetTextSize--normal js-tweet-text tweet-text\" data-aria-label-part=\"0\" lang=\"pt\">perfei\u00e7\u00e3o tem nome sim: <a class=\"twitter-timeline-link\" data-expanded-url=\"https:\/\/youtu.be\/6oanIo_2Z4Q\" dir=\"ltr\" href=\"https:\/\/t.co\/PCLHrqX8yG\" rel=\"nofollow noopener\" target=\"_blank\" title=\"https:\/\/youtu.be\/6oanIo_2Z4Q\"><span class=\"tco-ellipsis\"><\/span><span class=\"invisible\">https:\/\/<\/span><span class=\"js-display-url\">youtu.be\/6oanIo_2Z4Q<\/span><span class=\"invisible\"><\/span><span class=\"tco-ellipsis\"><span class=\"invisible\">\u00a0<\/span><\/span><\/a> perfeitas d+<\/p>","is_retweet":0,"likes":0,"replies":0,"retweet_id":"","retweeter_userid":"","retweeter_username":"","retweets":0,"text":"perfei\u00e7\u00e3o tem nome sim: https:\/\/youtu.be\/6oanIo_2Z4Q\u00a0 perfeitas d+","timestamp":1573392964000,"timestamp_epochs":1573392964,"tweet_id":"1193522713564000263","tweet_url":"\/l4dynara\/status\/1193522713564000263","user_id":"35552990","username":"l4dynara"},{"fullname":".","html":"<p class=\"TweetTextSize TweetTextSize--normal js-tweet-text tweet-text\" data-aria-label-part=\"0\" lang=\"pt\">Ana entenda que \u00e9 seu destino carregar o time nas costas<\/p>","is_retweet":1,"likes":1,"replies":0,"retweet_id":"1193279389280153600","retweeter_userid":"35552990","retweeter_username":"l4dynara","retweets":1,"text":"Ana entenda que \u00e9 seu destino carregar o time nas costas","timestamp":1573333722000,"timestamp_epochs":1573333722,"tweet_id":"1193274237219414020","tweet_url":"\/guihcf\/status\/1193274237219414020","user_id":"141415498","username":"guihcf"},{"fullname":"tainara","html":"<p class=\"TweetTextSize TweetTextSize--normal js-tweet-text tweet-text\" data-aria-label-part=\"0\" lang=\"en\">Rainha do game  <a class=\"twitter-hashtag pretty-link js-nav\" data-query-source=\"hashtag_click\" dir=\"ltr\" href=\"\/hashtag\/PS4share?src=hash\"><s>#<\/s><b>PS4share<\/b><\/a>\n<a class=\"twitter-timeline-link\" data-expanded-url=\"https:\/\/store.playstation.com\/#!\/pt-br\/tid=CUSA01842_00\" dir=\"ltr\" href=\"https:\/\/t.co\/CgEMGroLXX\" rel=\"nofollow noopener\" target=\"_blank\" title=\"https:\/\/store.playstation.com\/#!\/pt-br\/tid=CUSA01842_00\"><span class=\"tco-ellipsis\"><\/span><span class=\"invisible\">https:\/\/<\/span><span class=\"js-display-url\">store.playstation.com\/#!\/pt-br\/tid=C<\/span><span class=\"invisible\">USA01842_00<\/span><span class=\"tco-ellipsis\"><span class=\"invisible\">\u00a0<\/span>\u2026<\/span><\/a><a class=\"twitter-timeline-link u-hidden\" data-pre-embedded=\"true\" dir=\"ltr\" href=\"https:\/\/t.co\/MDfMLLoKoP\">pic.twitter.com\/MDfMLLoKoP<\/a><\/p>","is_retweet":0,"likes":2,"replies":2,"retweet_id":"","retweeter_userid":"","retweeter_username":"","retweets":0,"text":"Rainha do game  #PS4share\nhttps:\/\/store.playstation.com\/#!\/pt-br\/tid=CUSA01842_00\u00a0\u2026pic.twitter.com\/MDfMLLoKoP","timestamp":1573319535000,"timestamp_epochs":1573319535,"tweet_id":"1193214732444086272","tweet_url":"\/l4dynara\/status\/1193214732444086272","user_id":"35552990","username":"l4dynara"},{"fullname":"tainara","html":"<p class=\"TweetTextSize TweetTextSize--normal js-tweet-text tweet-text\" data-aria-label-part=\"0\" lang=\"pt\">eu s\u00f3 nao te mando tomar no cu pq eu estou mudando<\/p>","is_retweet":0,"likes":0,"replies":0,"retweet_id":"","retweeter_userid":"","retweeter_username":"","retweets":0,"text":"eu s\u00f3 nao te mando tomar no cu pq eu estou mudando","timestamp":1573243025000,"timestamp_epochs":1573243025,"tweet_id":"1192893827016773632","tweet_url":"\/l4dynara\/status\/1192893827016773632","user_id":"35552990","username":"l4dynara"},{"fullname":"tainara","html":"<p class=\"TweetTextSize TweetTextSize--normal js-tweet-text tweet-text\" data-aria-label-part=\"0\" lang=\"ro\">hr de colocar mukbang<\/p>","is_retweet":0,"likes":0,"replies":0,"retweet_id":"","retweeter_userid":"","retweeter_username":"","retweets":0,"text":"hr de colocar mukbang","timestamp":1573242411000,"timestamp_epochs":1573242411,"tweet_id":"1192891249558208514","tweet_url":"\/l4dynara\/status\/1192891249558208514","user_id":"35552990","username":"l4dynara"},{"fullname":"tainara","html":"<p class=\"TweetTextSize TweetTextSize--normal js-tweet-text tweet-text\" data-aria-label-part=\"4\" lang=\"pt\">na moral esse pa\u00eds t\u00e1 entregue mesmo<a class=\"twitter-timeline-link u-hidden\" data-expanded-url=\"https:\/\/twitter.com\/LulaOficial\/status\/1192888341584322562\" dir=\"ltr\" href=\"https:\/\/t.co\/E93CEhWJaf\" rel=\"nofollow noopener\" target=\"_blank\" title=\"https:\/\/twitter.com\/LulaOficial\/status\/1192888341584322562\"><span class=\"tco-ellipsis\"><\/span><span class=\"invisible\">https:\/\/<\/span><span class=\"js-display-url\">twitter.com\/LulaOficial\/st<\/span><span class=\"invisible\">atus\/1192888341584322562<\/span><span class=\"tco-ellipsis\"><span class=\"invisible\">\u00a0<\/span>\u2026<\/span><\/a><\/p>","is_retweet":0,"likes":2,"replies":1,"retweet_id":"","retweeter_userid":"","retweeter_username":"","retweets":0,"text":"na moral esse pa\u00eds t\u00e1 entregue mesmohttps:\/\/twitter.com\/LulaOficial\/status\/1192888341584322562\u00a0\u2026","timestamp":1573242093000,"timestamp_epochs":1573242093,"tweet_id":"1192889916776157187","tweet_url":"\/l4dynara\/status\/1192889916776157187","user_id":"35552990","username":"l4dynara"},{"fullname":"tainara","html":"<p class=\"TweetTextSize TweetTextSize--normal js-tweet-text tweet-text\" data-aria-label-part=\"4\" lang=\"en\">things to do before u die<a class=\"twitter-timeline-link u-hidden\" data-expanded-url=\"https:\/\/twitter.com\/visatisfatorios\/status\/1192872150870495232\" dir=\"ltr\" href=\"https:\/\/t.co\/b1o76M0oJP\" rel=\"nofollow noopener\" target=\"_blank\" title=\"https:\/\/twitter.com\/visatisfatorios\/status\/1192872150870495232\"><span class=\"tco-ellipsis\"><\/span><span class=\"invisible\">https:\/\/<\/span><span class=\"js-display-url\">twitter.com\/visatisfatorio<\/span><span class=\"invisible\">s\/status\/1192872150870495232<\/span><span class=\"tco-ellipsis\"><span class=\"invisible\">\u00a0<\/span>\u2026<\/span><\/a><\/p>","is_retweet":0,"likes":2,"replies":0,"retweet_id":"","retweeter_userid":"","retweeter_username":"","retweets":0,"text":"things to do before u diehttps:\/\/twitter.com\/visatisfatorios\/status\/1192872150870495232\u00a0\u2026","timestamp":1573237964000,"timestamp_epochs":1573237964,"tweet_id":"1192872597547028481","tweet_url":"\/l4dynara\/status\/1192872597547028481","user_id":"35552990","username":"l4dynara"},{"fullname":"tainara","html":"<p class=\"TweetTextSize TweetTextSize--normal js-tweet-text tweet-text\" data-aria-label-part=\"4\" lang=\"tl\">Nanao ficou IDENTICA a Koyanagi D:<a class=\"twitter-timeline-link u-hidden\" data-expanded-url=\"https:\/\/twitter.com\/Crunchyroll_PT\/status\/1192861180940947461\" dir=\"ltr\" href=\"https:\/\/t.co\/JkzOYwRqKk\" rel=\"nofollow noopener\" target=\"_blank\" title=\"https:\/\/twitter.com\/Crunchyroll_PT\/status\/1192861180940947461\"><span class=\"tco-ellipsis\"><\/span><span class=\"invisible\">https:\/\/<\/span><span class=\"js-display-url\">twitter.com\/Crunchyroll_PT<\/span><span class=\"invisible\">\/status\/1192861180940947461<\/span><span class=\"tco-ellipsis\"><span class=\"invisible\">\u00a0<\/span>\u2026<\/span><\/a><\/p>","is_retweet":0,"likes":1,"replies":0,"retweet_id":"","retweeter_userid":"","retweeter_username":"","retweets":0,"text":"Nanao ficou IDENTICA a Koyanagi D:https:\/\/twitter.com\/Crunchyroll_PT\/status\/1192861180940947461\u00a0\u2026","timestamp":1573235820000,"timestamp_epochs":1573235820,"tweet_id":"1192863604460134401","tweet_url":"\/l4dynara\/status\/1192863604460134401","user_id":"35552990","username":"l4dynara"},{"fullname":"tainara","html":"<p class=\"TweetTextSize TweetTextSize--normal js-tweet-text tweet-text\" data-aria-label-part=\"0\" lang=\"pt\">to presa nesse video<\/p>","is_retweet":0,"likes":0,"replies":0,"retweet_id":"","retweeter_userid":"","retweeter_username":"","retweets":0,"text":"to presa nesse video","timestamp":1573235323000,"timestamp_epochs":1573235323,"tweet_id":"1192861521619169280","tweet_url":"\/l4dynara\/status\/1192861521619169280","user_id":"35552990","username":"l4dynara"},{"fullname":"tainara","html":"<p class=\"TweetTextSize TweetTextSize--normal js-tweet-text tweet-text\" data-aria-label-part=\"0\" lang=\"de\">achei um novo video de beatbox fav<a class=\"twitter-timeline-link u-hidden\" data-expanded-url=\"https:\/\/www.youtube.com\/watch?v=t_QqOsXvJV8\" dir=\"ltr\" href=\"https:\/\/t.co\/2Dh9qR6b3B\" rel=\"nofollow noopener\" target=\"_blank\" title=\"https:\/\/www.youtube.com\/watch?v=t_QqOsXvJV8\"><span class=\"tco-ellipsis\"><\/span><span class=\"invisible\">https:\/\/www.<\/span><span class=\"js-display-url\">youtube.com\/watch?v=t_QqOs<\/span><span class=\"invisible\">XvJV8<\/span><span class=\"tco-ellipsis\"><span class=\"invisible\">\u00a0<\/span>\u2026<\/span><\/a><\/p>","is_retweet":0,"likes":0,"replies":1,"retweet_id":"","retweeter_userid":"","retweeter_username":"","retweets":0,"text":"achei um novo video de beatbox favhttps:\/\/www.youtube.com\/watch?v=t_QqOsXvJV8\u00a0\u2026","timestamp":1573235146000,"timestamp_epochs":1573235146,"tweet_id":"1192860779839705089","tweet_url":"\/l4dynara\/status\/1192860779839705089","user_id":"35552990","username":"l4dynara"},{"fullname":"luscas","html":"<p class=\"TweetTextSize TweetTextSize--normal js-tweet-text tweet-text\" data-aria-label-part=\"0\" lang=\"pt\">tarde gostosa pra tirar uma sonequinha e s\u00f3 acordar na hora da janta<\/p>","is_retweet":1,"likes":12805,"replies":43,"retweet_id":"1192854123542204419","retweeter_userid":"35552990","retweeter_username":"l4dynara","retweets":4738,"text":"tarde gostosa pra tirar uma sonequinha e s\u00f3 acordar na hora da janta","timestamp":1573233189000,"timestamp_epochs":1573233189,"tweet_id":"1192852571901313024","tweet_url":"\/luscas\/status\/1192852571901313024","user_id":"432983617","username":"luscas"},{"fullname":"tainara","html":"<p class=\"TweetTextSize TweetTextSize--normal js-tweet-text tweet-text\" data-aria-label-part=\"4\" lang=\"pt\">caralho ???????????????<a class=\"twitter-timeline-link u-hidden\" data-expanded-url=\"https:\/\/twitter.com\/Stray_Kids\/status\/1192819080773939200\" dir=\"ltr\" href=\"https:\/\/t.co\/5kHjHgbXoW\" rel=\"nofollow noopener\" target=\"_blank\" title=\"https:\/\/twitter.com\/Stray_Kids\/status\/1192819080773939200\"><span class=\"tco-ellipsis\"><\/span><span class=\"invisible\">https:\/\/<\/span><span class=\"js-display-url\">twitter.com\/Stray_Kids\/sta<\/span><span class=\"invisible\">tus\/1192819080773939200<\/span><span class=\"tco-ellipsis\"><span class=\"invisible\">\u00a0<\/span>\u2026<\/span><\/a><\/p>","is_retweet":0,"likes":0,"replies":0,"retweet_id":"","retweeter_userid":"","retweeter_username":"","retweets":0,"text":"caralho ???????????????https:\/\/twitter.com\/Stray_Kids\/status\/1192819080773939200\u00a0\u2026","timestamp":1573225613000,"timestamp_epochs":1573225613,"tweet_id":"1192820793861967880","tweet_url":"\/l4dynara\/status\/1192820793861967880","user_id":"35552990","username":"l4dynara"},{"fullname":"tainara","html":"<p class=\"TweetTextSize TweetTextSize--normal js-tweet-text tweet-text\" data-aria-label-part=\"0\" lang=\"ko\">EVERGLOW (\uc5d0\ubc84\uae00\ub85c\uc6b0) - Adios MV <a class=\"twitter-timeline-link\" data-expanded-url=\"https:\/\/youtu.be\/4gX_p1VkgA4\" dir=\"ltr\" href=\"https:\/\/t.co\/JxbFGCLJoV\" rel=\"nofollow noopener\" target=\"_blank\" title=\"https:\/\/youtu.be\/4gX_p1VkgA4\"><span class=\"tco-ellipsis\"><\/span><span class=\"invisible\">https:\/\/<\/span><span class=\"js-display-url\">youtu.be\/4gX_p1VkgA4<\/span><span class=\"invisible\"><\/span><span class=\"tco-ellipsis\"><span class=\"invisible\">\u00a0<\/span><\/span><\/a> via <a class=\"twitter-atreply pretty-link js-nav\" data-mentioned-user-id=\"10228272\" dir=\"ltr\" href=\"\/YouTube\"><s>@<\/s><b>YouTube<\/b><\/a><\/p>","is_retweet":0,"likes":0,"replies":0,"retweet_id":"","retweeter_userid":"","retweeter_username":"","retweets":0,"text":"EVERGLOW (\uc5d0\ubc84\uae00\ub85c\uc6b0) - Adios MV https:\/\/youtu.be\/4gX_p1VkgA4\u00a0 via @YouTube","timestamp":1573224613000,"timestamp_epochs":1573224613,"tweet_id":"1192816600518410240","tweet_url":"\/l4dynara\/status\/1192816600518410240","user_id":"35552990","username":"l4dynara"},{"fullname":"memes tristes","html":"<p class=\"TweetTextSize TweetTextSize--normal js-tweet-text tweet-text\" data-aria-label-part=\"0\" lang=\"und\"><a class=\"twitter-timeline-link u-hidden\" data-pre-embedded=\"true\" dir=\"ltr\" href=\"https:\/\/t.co\/hCt617K5uG\">pic.twitter.com\/hCt617K5uG<\/a><\/p>","is_retweet":1,"likes":5050,"replies":16,"retweet_id":"1192793811388420097","retweeter_userid":"35552990","retweeter_username":"l4dynara","retweets":1970,"text":"pic.twitter.com\/hCt617K5uG","timestamp":1573218874000,"timestamp_epochs":1573218874,"tweet_id":"1192792527449083904","tweet_url":"\/flypz\/status\/1192792527449083904","user_id":"1086247216258433024","username":"flypz"},{"fullname":"tainara","html":"<p class=\"TweetTextSize TweetTextSize--normal js-tweet-text tweet-text\" data-aria-label-part=\"0\" lang=\"pt\">hwasa pq t\u00e3o dona da coreia<\/p>","is_retweet":0,"likes":0,"replies":0,"retweet_id":"","retweeter_userid":"","retweeter_username":"","retweets":0,"text":"hwasa pq t\u00e3o dona da coreia","timestamp":1573219165000,"timestamp_epochs":1573219165,"tweet_id":"1192793750201864192","tweet_url":"\/l4dynara\/status\/1192793750201864192","user_id":"35552990","username":"l4dynara"},{"fullname":"tainara","html":"<p class=\"TweetTextSize TweetTextSize--normal js-tweet-text tweet-text\" data-aria-label-part=\"0\" lang=\"und\"><a class=\"twitter-timeline-link u-hidden\" data-expanded-url=\"https:\/\/www.youtube.com\/watch?v=ScSn235gQx0\" dir=\"ltr\" href=\"https:\/\/t.co\/KRM0YIzaQE\" rel=\"nofollow noopener\" target=\"_blank\" title=\"https:\/\/www.youtube.com\/watch?v=ScSn235gQx0\"><span class=\"tco-ellipsis\"><\/span><span class=\"invisible\">https:\/\/www.<\/span><span class=\"js-display-url\">youtube.com\/watch?v=ScSn23<\/span><span class=\"invisible\">5gQx0<\/span><span class=\"tco-ellipsis\"><span class=\"invisible\">\u00a0<\/span>\u2026<\/span><\/a><\/p>","is_retweet":0,"likes":0,"replies":1,"retweet_id":"","retweeter_userid":"","retweeter_username":"","retweets":0,"text":"https:\/\/www.youtube.com\/watch?v=ScSn235gQx0\u00a0\u2026","timestamp":1573219141000,"timestamp_epochs":1573219141,"tweet_id":"1192793649744109569","tweet_url":"\/l4dynara\/status\/1192793649744109569","user_id":"35552990","username":"l4dynara"},{"fullname":"tainara","html":"<p class=\"TweetTextSize TweetTextSize--normal js-tweet-text tweet-text\" data-aria-label-part=\"0\" lang=\"pt\">bonus: depois a mulher tbm virou homem<\/p>","is_retweet":0,"likes":0,"replies":0,"retweet_id":"","retweeter_userid":"","retweeter_username":"","retweets":0,"text":"bonus: depois a mulher tbm virou homem","timestamp":1573217861000,"timestamp_epochs":1573217861,"tweet_id":"1192788281404133376","tweet_url":"\/l4dynara\/status\/1192788281404133376","user_id":"35552990","username":"l4dynara"},{"fullname":"tainara","html":"<p class=\"TweetTextSize TweetTextSize--normal js-tweet-text tweet-text\" data-aria-label-part=\"0\" lang=\"pt\">Esse ted talk entrou pra um dos meus favs junto com o da mulher q casou com um cara q depois virou mulher k<\/p>","is_retweet":0,"likes":0,"replies":1,"retweet_id":"","retweeter_userid":"","retweeter_username":"","retweets":0,"text":"Esse ted talk entrou pra um dos meus favs junto com o da mulher q casou com um cara q depois virou mulher k","timestamp":1573217294000,"timestamp_epochs":1573217294,"tweet_id":"1192785901375688705","tweet_url":"\/l4dynara\/status\/1192785901375688705","user_id":"35552990","username":"l4dynara"},{"fullname":"tainara","html":"<p class=\"TweetTextSize TweetTextSize--normal js-tweet-text tweet-text\" data-aria-label-part=\"0\" lang=\"und\"><a class=\"twitter-timeline-link u-hidden\" data-expanded-url=\"https:\/\/www.youtube.com\/watch?v=DTcJmIbn5nw\" dir=\"ltr\" href=\"https:\/\/t.co\/q9WWjFAgAO\" rel=\"nofollow noopener\" target=\"_blank\" title=\"https:\/\/www.youtube.com\/watch?v=DTcJmIbn5nw\"><span class=\"tco-ellipsis\"><\/span><span class=\"invisible\">https:\/\/www.<\/span><span class=\"js-display-url\">youtube.com\/watch?v=DTcJmI<\/span><span class=\"invisible\">bn5nw<\/span><span class=\"tco-ellipsis\"><span class=\"invisible\">\u00a0<\/span>\u2026<\/span><\/a><\/p>","is_retweet":0,"likes":0,"replies":0,"retweet_id":"","retweeter_userid":"","retweeter_username":"","retweets":0,"text":"https:\/\/www.youtube.com\/watch?v=DTcJmIbn5nw\u00a0\u2026","timestamp":1573217257000,"timestamp_epochs":1573217257,"tweet_id":"1192785747578937345","tweet_url":"\/l4dynara\/status\/1192785747578937345","user_id":"35552990","username":"l4dynara"},{"fullname":"tainara","html":"<p class=\"TweetTextSize TweetTextSize--normal js-tweet-text tweet-text\" data-aria-label-part=\"4\" lang=\"und\">KKKKKKKKKKKKKKKKKKKKKKKKKKKKKKKKKKKKKKKKKKKKKKKKKKKKKKKKKKKKKKKK<a class=\"twitter-timeline-link u-hidden\" data-expanded-url=\"https:\/\/twitter.com\/igorrealequatro\/status\/1192774904434876416\" dir=\"ltr\" href=\"https:\/\/t.co\/ksDJMPgr5J\" rel=\"nofollow noopener\" target=\"_blank\" title=\"https:\/\/twitter.com\/igorrealequatro\/status\/1192774904434876416\"><span class=\"tco-ellipsis\"><\/span><span class=\"invisible\">https:\/\/<\/span><span class=\"js-display-url\">twitter.com\/igorrealequatr<\/span><span class=\"invisible\">o\/status\/1192774904434876416<\/span><span class=\"tco-ellipsis\"><span class=\"invisible\">\u00a0<\/span>\u2026<\/span><\/a><\/p>","is_retweet":0,"likes":0,"replies":0,"retweet_id":"","retweeter_userid":"","retweeter_username":"","retweets":0,"text":"KKKKKKKKKKKKKKKKKKKKKKKKKKKKKKKKKKKKKKKKKKKKKKKKKKKKKKKKKKKKKKKKhttps:\/\/twitter.com\/igorrealequatro\/status\/1192774904434876416\u00a0\u2026","timestamp":1573214997000,"timestamp_epochs":1573214997,"tweet_id":"1192776267319390214","tweet_url":"\/l4dynara\/status\/1192776267319390214","user_id":"35552990","username":"l4dynara"}]